{
  "units": {
    "unit": [
      {
        "typeName": "f-4e_kurnass_2000",
        "AoA1": 11,
        "AoA2": 15,
        "volume": 50
      },
      {
        "typeName": "f-8e_fn",
        "AoA1": 8,
        "AoA2": 12,
        "volume": 50
      },
      {
        "typeName": "f_16a_block_10_iaf",
        "AoA1": 11,
        "AoA2": 14,
        "volume": 50
      },
      {
        "typeName": "F-16C_50",
        "AoA1": 11,
        "AoA2": 14,
        "volume": 50
      },
      {
        "typeName": "f_16d_block_40_barak_2",
        "AoA1": 11,
        "AoA2": 14,
        "volume": 50
      },
      {
        "typeName": "FA-18C_hornet",
        "AoA1": 11,
        "AoA2": 15,
        "volume": 50
      },
      {
        "typeName": "F-14A-135-GR",
        "AoA1": 8,
        "AoA2": 12,
        "volume": 50
      },
      {
        "typeName": "F-14B",
        "AoA1": 8,
        "AoA2": 12,
        "volume": 50
      },
      {
        "typeName": "F-15C",
        "AoA1": 9,
        "AoA2": 13,
        "volume": 50
      },
      {
        "typeName": "f_15a_iaf",
        "AoA1": 9,
        "AoA2": 13,
        "volume": 50
      },
      {
        "typeName": "MiG-29A",
        "AoA1": 10,
        "AoA2": 14,
        "volume": 50
      },
      {
        "typeName": "Su-27",
        "AoA1": 11,
        "AoA2": 15,
        "volume": 50
      },
      {
        "typeName": "Su-33",
        "AoA1": 11,
        "AoA2": 15,
        "volume": 50
      },
      {
        "typeName": "F-5E-3",
        "AoA1": 8,
        "AoA2": 11,
        "volume": 50
      },
      {
        "typeName": "f-5c",
        "AoA1": 8,
        "AoA2": 11,
        "volume": 50
      },
      {
        "typeName": "f_5c_turkey",
        "AoA1": 8,
        "AoA2": 11,
        "volume": 50
      },
      {
        "typeName": "kfir_c7",
        "AoA1": 8,
        "AoA2": 12,
        "volume": 50
      },
      {
        "typeName": "mirage_milan",
        "AoA1": 8,
        "AoA2": 12,
        "volume": 50
      },
      {
        "typeName": "mirage_3cj",
        "AoA1": 8,
        "AoA2": 12,
        "volume": 50
      },
      {
        "typeName": "nesher",
        "AoA1": 8,
        "AoA2": 12,
        "volume": 50
      },
      {
        "typeName": "alpha_jet_e",
        "AoA1": 7,
        "AoA2": 12,
        "volume": 50
      },
      {
        "typeName": "mirage_f1c_200",
        "AoA1": 8,
        "AoA2": 12,
        "volume": 50
      },
      {
        "typeName": "a_4e_early_iaf",
        "AoA1": 8,
        "AoA2": 12,
        "volume": 50
      }
    ]
  }
}